README.md
decorator_http.py
setup.py
decorator_http.egg-info/PKG-INFO
decorator_http.egg-info/SOURCES.txt
decorator_http.egg-info/dependency_links.txt
decorator_http.egg-info/requires.txt
decorator_http.egg-info/top_level.txt