Metadata-Version: 2.1
Name: decorator_http
Version: 0.0.6
Summary: A easy way to use requests but with decorators
Author: Paulo Henrique
Author-email: contact@paulohenriquesn.com
Classifier: Programming Language :: Python :: 3
Classifier: License :: OSI Approved :: MIT License
Classifier: Operating System :: OS Independent
Requires-Python: >=3.6
Requires-Dist: requests
